<?xml version="1.0" encoding="UTF-8"?>
<tt xmlns="http://www.w3.org/2006/10/ttaf1" xmlns:ttp="http://www.w3.org/2006/10/ttaf1#parameter" ttp:timeBase="media" xmlns:tts="http://www.w3.org/2006/10/ttaf1#style" xml:lang="en" xmlns:ttm="http://www.w3.org/2006/10/ttaf1#metadata">
<head>
<styling>
  <style id="s0" style="s0"/>
</styling>
</head><body tts:textAlign="center" style="s0">
<div>
<p begin = "00:00:03.392" dur="00:00:05.00"><span tts:color="#ededed" tts:textAlign="left"> Hiya, <br/></span></p>
<p begin = "00:00:04.432" dur="00:00:05.00"><span tts:color="#ededed" tts:textAlign="center">you're </span><br/></p>
<p begin = "00:00:04.552" dur="00:00:05.00"><span tts:color="#ededed" tts:textAlign="center">with </span></p>
<p begin = "00:00:04.552" dur="00:00:05.00"><span tts:color="#ededed" tts:textAlign="center">with Newsround. </span></p>
<p begin = "00:00:04.752" dur="00:00:05.00"><span tts:color="#ededed" tts:textAlign="center">with Newsround.  It's </span></p>
<p begin = "00:00:05.112" dur="00:00:05.00"><span tts:color="#ededed" tts:textAlign="center"> Hiya, you're with Newsround. It's </span><br/></p>
<p begin = "00:00:05.112" dur="00:00:05.00"><span tts:color="#ededed" tts:textAlign="center"> Hiya, you're with Newsround. It's <br/> Tuesday </span></p>
<p begin = "00:00:05.352" dur="00:00:05.00"><span tts:color="#ededed" tts:textAlign="center"> Hiya, you're with Newsround. It's <br/> Tuesday morning. </span></p>
<p begin = "00:00:06.672" dur="00:00:05.00"><span tts:color="#ededed" tts:textAlign="center"> Hiya, you're with Newsround. It's <br/> Tuesday morning.  First </span></p>
<p begin = "00:00:06.912" dur="00:00:05.00"><span tts:color="#ededed" tts:textAlign="center"> Hiya, you're with Newsround. It's <br/> Tuesday morning.  First up </span></p>
<p begin = "00:00:07.232" dur="00:00:05.00"><span tts:color="#ededed" tts:textAlign="center"> Hiya, you're with Newsround. It's <br/> Tuesday morning.  First up news </span></p>
<p begin = "00:00:07.472" dur="00:00:05.00"><span tts:color="#ededed" tts:textAlign="center"> Hiya, you're with Newsround. It's <br/> Tuesday morning.  First up news of </span></p>
<p begin = "00:00:07.672" dur="00:00:05.00"><span tts:color="#ededed" tts:textAlign="center"> Hiya, you're with Newsround. It's <br/> Tuesday morning.  First up news of a</span></p>
<p begin = "00:00:07.952" dur="00:00:05.00"><span tts:color="#ededed" tts:textAlign="center"> Tuesday morning. First up news of a </span><br/></p>
<p begin = "00:00:07.952" dur="00:00:05.00"><span tts:color="#ededed" tts:textAlign="center"> Tuesday morning. First up news of a <br/> big </span></p>
<p begin = "00:00:08.152" dur="00:00:05.00"><span tts:color="#ededed" tts:textAlign="center"> Tuecelebration </span></p>
<p begin = "00:00:08.512" dur="00:00:05.00"><span tts:color="#ededed" tts:textAlign="center"> Tueceleto </span></p>
<p begin = "00:00:08.752" dur="00:00:05.00"><span tts:color="#ededed" tts:textAlign="center"> Tueceleto mark </span></p>
<p begin = "00:00:08.992" dur="00:00:05.00"><span tts:color="#ededed" tts:textAlign="center"> Tueceleto mark the </span></p>
<p begin = "00:00:09.192" dur="00:00:05.00"><span tts:color="#ededed" tts:textAlign="center"> Tueceleto mark the hand </span></p>
<p begin = "00:00:09.432" dur="00:00:05.00"><span tts:color="#ededed" tts:textAlign="center"> big celebration to mark the hand </span><br/></p>
<p begin = "00:00:09.432" dur="00:00:05.00"><span tts:color="#ededed" tts:textAlign="center"> big celebration to mark the hand <br/> over </span></p>
<p begin = "00:00:09.672" dur="00:00:05.00"><span tts:color="#ededed" tts:textAlign="center"> big celebration to mark the hanof </span></p>
<p begin = "00:00:10.032" dur="00:00:05.00"><span tts:color="#ededed" tts:textAlign="center"> big celebration to mark the hanof the </span></p>
<p begin = "00:00:10.272" dur="00:00:05.00"><span tts:color="#ededed" tts:textAlign="center"> big celebration to mark the hanof the Olympic </span></p>
<p begin = "00:00:10.512" dur="00:00:05.00"><span tts:color="#ededed" tts:textAlign="center"> big celebration to mark the hanof the Olympgames </span></p>
<p begin = "00:00:10.672" dur="00:00:05.00"><span tts:color="#ededed" tts:textAlign="center"> big celebration to mark the hanof the Olympgamefrom </span></p>
<p begin = "00:00:10.912" dur="00:00:05.00"><span tts:color="#ededed" tts:textAlign="center"> over of the Olympic games from </span><br/></p>
<p begin = "00:00:10.912" dur="00:00:05.00"><span tts:color="#ededed" tts:textAlign="center"> over of the Olympic games from <br/> China </span></p>
<p begin = "00:00:11.192" dur="00:00:05.00"><span tts:color="#ededed" tts:textAlign="center"> over of the Olympic games from <br/> China to </span></p>
<p begin = "00:00:11.512" dur="00:00:05.00"><span tts:color="#ededed" tts:textAlign="center"> over of the Olympic games from <br/> China to London. </span></p>
<p begin = "00:00:13.341" dur="00:00:05.00"><span tts:color="#ededed" tts:textAlign="center"> over of the Olympic games from <br/> China to London.  The </span></p>
<p begin = "00:00:13.541" dur="00:00:05.00"><span tts:color="#ededed" tts:textAlign="center"> over of the Olympic games from <br/> China to London.  The City's </span></p>
<p begin = "00:00:13.781" dur="00:00:05.00"><span tts:color="#ededed" tts:textAlign="center"> over of the Olympic games from <br/> China to London.  The City's not </span></p>
<p begin = "00:00:13.981" dur="00:00:05.00"><span tts:color="#ededed" tts:textAlign="center"> China to London. The City's not </span><br/></p>
<p begin = "00:00:13.981" dur="00:00:05.00"><span tts:color="#ededed" tts:textAlign="center"> China to London. The City's not <br/> hosting </span></p>
<p begin = "00:00:14.341" dur="00:00:05.00"><span tts:color="#ededed" tts:textAlign="center"> China to London. The City's not <br/> hosting the </span></p>
<p begin = "00:00:14.581" dur="00:00:05.00"><span tts:color="#ededed" tts:textAlign="center"> China to London. The City's not <br/> hosting the games </span></p>
<p begin = "00:00:14.821" dur="00:00:05.00"><span tts:color="#ededed" tts:textAlign="center"> China to London. The City's not <br/> hosting the games until </span></p>
<p begin = "00:00:15.021" dur="00:00:05.00"><span tts:color="#ededed" tts:textAlign="center"> China to London. The City's not <br/> hosting the games until 2012 </span></p>
<p begin = "00:00:15.261" dur="00:00:05.00"><span tts:color="#ededed" tts:textAlign="center"> China to London. The City's not <br/> hosting the games until 2012 but </span></p>
<p begin = "00:00:15.581" dur="00:00:05.00"><span tts:color="#ededed" tts:textAlign="center"> hosting the games until 2012 but </span><br/></p>
<p begin = "00:00:15.581" dur="00:00:05.00"><span tts:color="#ededed" tts:textAlign="center"> hosting the games until 2012 but <br/> they're </span></p>
<p begin = "00:00:15.861" dur="00:00:05.00"><span tts:color="#ededed" tts:textAlign="center"> hosting the games until 2012 but <br/> they're kicking </span></p>
<p begin = "00:00:16.061" dur="00:00:05.00"><span tts:color="#ededed" tts:textAlign="center"> hosting the games until 2012 but <br/> they're kicking the </span></p>
<p begin = "00:00:16.341" dur="00:00:05.00"><span tts:color="#ededed" tts:textAlign="center"> hosting the games until 2012 but <br/> they're kicking the party </span></p>
<p begin = "00:00:16.541" dur="00:00:05.00"><span tts:color="#ededed" tts:textAlign="center"> hosting the games until 2012 but <br/> they're kicking the party off </span></p>
<p begin = "00:00:16.781" dur="00:00:05.00"><span tts:color="#ededed" tts:textAlign="center"> hosting the games until 2012 but <br/> they're kicking the party off early </span></p>
<p begin = "00:00:17.101" dur="00:00:05.00"><span tts:color="#ededed" tts:textAlign="center"> they're kicking the party off early </span><br/></p>
<p begin = "00:00:17.101" dur="00:00:05.00"><span tts:color="#ededed" tts:textAlign="center"> they're kicking the party off early <br/> by </span></p>
<p begin = "00:00:17.341" dur="00:00:05.00"><span tts:color="#ededed" tts:textAlign="center"> they're kicking the party off early <br/> by holding </span></p>
<p begin = "00:00:17.581" dur="00:00:05.00"><span tts:color="#ededed" tts:textAlign="center"> they're kicking the party off early <br/> by holding a </span></p>
<p begin = "00:00:17.821" dur="00:00:05.00"><span tts:color="#ededed" tts:textAlign="center"> they're kicking the party off early <br/> by holding a free </span></p>
<p begin = "00:00:18.021" dur="00:00:05.00"><span tts:color="#ededed" tts:textAlign="center"> they're kicking the party off early <br/> by holding a free concert </span></p>
<p begin = "00:00:18.381" dur="00:00:05.00"><span tts:color="#ededed" tts:textAlign="center"> they're kicking the party off early <br/> by holding a free concert for </span></p>
<p begin = "00:00:18.581" dur="00:00:05.00"><span tts:color="#ededed" tts:textAlign="center"> by holding a free concert for </span><br/></p>
<p begin = "00:00:18.581" dur="00:00:05.00"><span tts:color="#ededed" tts:textAlign="center"> by holding a free concert for <br/> 40,000 </span></p>
<p begin = "00:00:18.821" dur="00:00:05.00"><span tts:color="#ededed" tts:textAlign="center"> by holding a free concert for <br/> 40,000 people </span></p>
<p begin = "00:00:19.101" dur="00:00:05.00"><span tts:color="#ededed" tts:textAlign="center"> by holding a free concert for <br/> 40,000 people in </span></p>
<p begin = "00:00:19.341" dur="00:00:05.00"><span tts:color="#ededed" tts:textAlign="center"> by holding a free concert for <br/> 40,000 people in August, </span></p>
<p begin = "00:00:19.701" dur="00:00:05.00"><span tts:color="#ededed" tts:textAlign="center"> by holding a free concert for <br/> 40,000 people in August, as </span></p>
<p begin = "00:00:19.901" dur="00:00:05.00"><span tts:color="#ededed" tts:textAlign="center"> by holding a free concert for <br/> 40,000 people in August, as the </span></p>
<p begin = "00:00:20.141" dur="00:00:05.00"><span tts:color="#ededed" tts:textAlign="center"> 40,000 people in August, as the </span><br/></p>
<p begin = "00:00:20.141" dur="00:00:05.00"><span tts:color="#ededed" tts:textAlign="center"> 40,000 people in August, as the <br/> Bejing </span></p>
<p begin = "00:00:20.341" dur="00:00:05.00"><span tts:color="#ededed" tts:textAlign="center"> 40,000 people in August, as the <br/> Bejing games </span></p>
<p begin = "00:00:20.581" dur="00:00:05.00"><span tts:color="#ededed" tts:textAlign="center"> 40,000 people in August, as the <br/> Bejing games end. </span></p>
<p begin = "00:00:27.203" dur="00:00:05.00"><span tts:color="#ededed" tts:textAlign="center"> 40,000 people in August, as the <br/> Bejing games end.  - </span></p>
<p begin = "00:00:27.443" dur="00:00:05.00"><span tts:color="#ededed" tts:textAlign="center"> 40,000 people in August, as the <br/> Bejing games end.  - Beijing </span></p>
<p begin = "00:00:27.683" dur="00:00:05.00"><span tts:color="#ededed" tts:textAlign="center"> 40,000 people in August, as the <br/> Bejing games end.  - Beijing Games. </span></p>
<p begin = "00:00:28.843" dur="00:00:05.00"><span tts:color="#ededed" tts:textAlign="center"> Bejing games end. - Beijing Games. </span><br/></p>
<p begin = "00:00:28.843" dur="00:00:05.00"><span tts:color="#ededed" tts:textAlign="center"> Bejing games end. - Beijing Games. <br/> And </span></p>
<p begin = "00:00:29.083" dur="00:00:05.00"><span tts:color="#ededed" tts:textAlign="center"> Bejing games end. - Beijing Games. <br/> And some </span></p>
<p begin = "00:00:29.283" dur="00:00:05.00"><span tts:color="#ededed" tts:textAlign="center"> Bejing games end. - Beijing Games. <br/> And some of </span></p>
<p begin = "00:00:29.683" dur="00:00:05.00"><span tts:color="#ededed" tts:textAlign="center"> Bejing games end. - Beijing Games. <br/> And some of the </span></p>
<p begin = "00:00:29.923" dur="00:00:05.00"><span tts:color="#ededed" tts:textAlign="center"> Bejing games end. - Beijing Games. <br/> And some of the biggest </span></p>
<p begin = "00:00:30.123" dur="00:00:05.00"><span tts:color="#ededed" tts:textAlign="center"> Bejing games end. - Beijing Games. <br/> And some of the biggest names </span></p>
<p begin = "00:00:30.323" dur="00:00:05.00"><span tts:color="#ededed" tts:textAlign="center"> Bejing games end. - Beijing Games. <br/> And some of the biggest names in </span></p>
<p begin = "00:00:30.603" dur="00:00:05.00"><span tts:color="#ededed" tts:textAlign="center"> And some of the biggest names in </span><br/></p>
<p begin = "00:00:30.603" dur="00:00:05.00"><span tts:color="#ededed" tts:textAlign="center"> And some of the biggest names in <br/> pop </span></p>
<p begin = "00:00:30.803" dur="00:00:05.00"><span tts:color="#ededed" tts:textAlign="center"> And some of the biggest names in <br/> pop were </span></p>
<p begin = "00:00:31.163" dur="00:00:05.00"><span tts:color="#ededed" tts:textAlign="center"> And some of the biggest names in <br/> pop were out </span></p>
<p begin = "00:00:31.403" dur="00:00:05.00"><span tts:color="#ededed" tts:textAlign="center"> And some of the biggest names in <br/> pop were out partying </span></p>
<p begin = "00:00:31.643" dur="00:00:05.00"><span tts:color="#ededed" tts:textAlign="center"> And some of the biggest names in <br/> pop were out partying last </span></p>
<p begin = "00:00:31.883" dur="00:00:05.00"><span tts:color="#ededed" tts:textAlign="center"> And some of the biggest names in <br/> pop were out partying last night </span></p>
<p begin = "00:00:32.083" dur="00:00:05.00"><span tts:color="#ededed" tts:textAlign="center"> pop were out partying last night </span><br/></p>
<p begin = "00:00:32.083" dur="00:00:05.00"><span tts:color="#ededed" tts:textAlign="center"> pop were out partying last night <br/> for </span></p>
<p begin = "00:00:32.443" dur="00:00:05.00"><span tts:color="#ededed" tts:textAlign="center"> pop were out partying last night <br/> for the </span></p>
<p begin = "00:00:32.683" dur="00:00:05.00"><span tts:color="#ededed" tts:textAlign="center"> pop were out partying last night <br/> for the MOJO </span></p>
<p begin = "00:00:32.883" dur="00:00:05.00"><span tts:color="#ededed" tts:textAlign="center"> pop were out partying last night <br/> for the MOJO Awards. </span></p>
<p begin = "00:00:33.603" dur="00:00:05.00"><span tts:color="#ededed" tts:textAlign="center"> pop were out partying last night <br/> for the MOJO Awards.  Chart </span></p>
<p begin = "00:00:33.843" dur="00:00:05.00"><span tts:color="#ededed" tts:textAlign="center"> for the MOJO Awards. Chart </span><br/></p>
<p begin = "00:00:33.843" dur="00:00:05.00"><span tts:color="#ededed" tts:textAlign="center"> for the MOJO Awards. Chart <br/> favourite, </span></p>
<p begin = "00:00:34.203" dur="00:00:05.00"><span tts:color="#ededed" tts:textAlign="center"> for the MOJO Awards. Chart <br/> favourite, Welsh </span></p>
<p begin = "00:00:34.443" dur="00:00:05.00"><span tts:color="#ededed" tts:textAlign="center"> for the MOJO Awards. Chart <br/> favourite, Welsh singer </span></p>
<p begin = "00:00:34.643" dur="00:00:05.00"><span tts:color="#ededed" tts:textAlign="center"> for the MOJO Awards. Chart <br/> favourite, Welsh singer Duffy, </span></p>
<p begin = "00:00:34.883" dur="00:00:05.00"><span tts:color="#ededed" tts:textAlign="center"> favourite, Welsh singer Duffy, </span><br/></p>
<p begin = "00:00:34.883" dur="00:00:05.00"><span tts:color="#ededed" tts:textAlign="center"> favourite, Welsh singer Duffy, <br/> picked </span></p>
<p begin = "00:00:35.123" dur="00:00:05.00"><span tts:color="#ededed" tts:textAlign="center"> favourite, Welsh singer Duffy, <br/> picked up </span></p>
<p begin = "00:00:35.363" dur="00:00:05.00"><span tts:color="#ededed" tts:textAlign="center"> favourite, Welsh singer Duffy, <br/> picked up an </span></p>
<p begin = "00:00:35.683" dur="00:00:05.00"><span tts:color="#ededed" tts:textAlign="center"> favourite, Welsh singer Duffy, <br/> picked up an award </span></p>
<p begin = "00:00:35.923" dur="00:00:05.00"><span tts:color="#ededed" tts:textAlign="center"> favourite, Welsh singer Duffy, <br/> picked up an award for </span></p>
<p begin = "00:00:36.163" dur="00:00:05.00"><span tts:color="#ededed" tts:textAlign="center"> favourite, Welsh singer Duffy, <br/> picked up an award for best </span></p>
<p begin = "00:00:36.403" dur="00:00:05.00"><span tts:color="#ededed" tts:textAlign="center"> favourite, Welsh singer Duffy, <br/> picked up an award for best for </span></p>
<p begin = "00:00:36.603" dur="00:00:05.00"><span tts:color="#ededed" tts:textAlign="center"> favourite, Welsh singer Duffy, <br/> picked up an award for best for her </span></p>
<p begin = "00:00:36.843" dur="00:00:05.00"><span tts:color="#ededed" tts:textAlign="center"> picked up an award for best for her </span><br/></p>
<p begin = "00:00:36.843" dur="00:00:05.00"><span tts:color="#ededed" tts:textAlign="center"> picked up an award for best for her <br/> massive </span></p>
<p begin = "00:00:37.203" dur="00:00:05.00"><span tts:color="#ededed" tts:textAlign="center"> picked up an award for best for her <br/> massive hit, </span></p>
<p begin = "00:00:37.443" dur="00:00:05.00"><span tts:color="#ededed" tts:textAlign="center"> picked up an award for best for her <br/> massive hit, Mercy, </span></p>
<p begin = "00:00:37.643" dur="00:00:05.00"><span tts:color="#ededed" tts:textAlign="center"> picked up an award for best for her <br/> massive hit, Mercy, and </span></p>
<p begin = "00:00:37.883" dur="00:00:05.00"><span tts:color="#ededed" tts:textAlign="center"> picked up an award for best for her <br/> massive hit, Mercy, and old </span></p>
<p begin = "00:00:38.123" dur="00:00:05.00"><span tts:color="#ededed" tts:textAlign="center"> picked up an award for best for her <br/> massive hit, Mercy, and old school </span></p>
<p begin = "00:00:38.483" dur="00:00:05.00"><span tts:color="#ededed" tts:textAlign="center"> massive hit, Mercy, and old school </span><br/></p>
<p begin = "00:00:38.483" dur="00:00:05.00"><span tts:color="#ededed" tts:textAlign="center"> massive hit, Mercy, and old school <br/> rockers </span></p>
<p begin = "00:00:38.683" dur="00:00:05.00"><span tts:color="#ededed" tts:textAlign="center"> massive hit, Mercy, and old school <br/> rockers Led </span></p>
<p begin = "00:00:38.923" dur="00:00:05.00"><span tts:color="#ededed" tts:textAlign="center"> massive hit, Mercy, and old school <br/> rockers Led Zeppelin </span></p>
<p begin = "00:00:39.163" dur="00:00:05.00"><span tts:color="#ededed" tts:textAlign="center"> massive hit, Mercy, and old school <br/> rockers Led Zeppelin also </span></p>
<p begin = "00:00:39.403" dur="00:00:05.00"><span tts:color="#ededed" tts:textAlign="center"> massive hit, Mercy, and old school <br/> rockers Led Zeppelin also walked </span></p>
<p begin = "00:00:39.603" dur="00:00:05.00"><span tts:color="#ededed" tts:textAlign="center"> rockers Led Zeppelin also walked </span><br/></p>
<p begin = "00:00:39.603" dur="00:00:05.00"><span tts:color="#ededed" tts:textAlign="center"> rockers Led Zeppelin also walked <br/> away </span></p>
<p begin = "00:00:39.963" dur="00:00:05.00"><span tts:color="#ededed" tts:textAlign="center"> rockers Led Zeppelin also walked <br/> away with </span></p>
<p begin = "00:00:40.203" dur="00:00:05.00"><span tts:color="#ededed" tts:textAlign="center"> rockers Led Zeppelin also walked <br/> away with ai</span></p>
<p begin = "00:00:40.443" dur="00:00:05.00"><span tts:color="#ededed" tts:textAlign="center"> rockers Led Zeppelin also walked <br/> away with aiprize. </span></p>
<p begin = "00:00:41.363" dur="00:00:05.00"><span tts:color="#ededed" tts:textAlign="center"> away with a prize. </span><br/></p>
<p begin = "00:00:41.363" dur="00:00:05.00"><span tts:color="#ededed" tts:textAlign="center"> away with a prize. <br/> Going </span></p>
<p begin = "00:00:41.603" dur="00:00:05.00"><span tts:color="#ededed" tts:textAlign="center"> away with a prize. <br/> Going to </span></p>
<p begin = "00:00:41.843" dur="00:00:05.00"><span tts:color="#ededed" tts:textAlign="center"> away with a prize. <br/> Going to the </span></p>
<p begin = "00:00:42.203" dur="00:00:05.00"><span tts:color="#ededed" tts:textAlign="center"> away with a prize. <br/> Going to the cinema </span></p>
<p begin = "00:00:42.443" dur="00:00:05.00"><span tts:color="#ededed" tts:textAlign="center"> away with a prize. <br/> Going to the cinema with </span></p>
<p begin = "00:00:42.643" dur="00:00:05.00"><span tts:color="#ededed" tts:textAlign="center"> away with a prize. <br/> Going to the cinema with your </span></p>
<p begin = "00:00:42.883" dur="00:00:05.00"><span tts:color="#ededed" tts:textAlign="center"> away with a prize. <br/> Going to the cinema with your mates </span></p>
<p begin = "00:00:43.083" dur="00:00:05.00"><span tts:color="#ededed" tts:textAlign="center"> Going to the cinema with your mates </span><br/></p>
<p begin = "00:00:43.083" dur="00:00:05.00"><span tts:color="#ededed" tts:textAlign="center"> Going to the cinema with your mates <br/> is </span></p>
<p begin = "00:00:43.363" dur="00:00:05.00"><span tts:color="#ededed" tts:textAlign="center"> Going to the cinema with your mates <br/> is fun, </span></p>
<p begin = "00:00:43.683" dur="00:00:05.00"><span tts:color="#ededed" tts:textAlign="center"> Going to the cinema with your mates <br/> is fun, but </span></p>
<p begin = "00:00:43.923" dur="00:00:05.00"><span tts:color="#ededed" tts:textAlign="center"> Going to the cinema with your mates <br/> is fun, but it </span></p>
<p begin = "00:00:44.163" dur="00:00:05.00"><span tts:color="#ededed" tts:textAlign="center"> Going to the cinema with your mates <br/> is fun, but it can </span></p>
<p begin = "00:00:44.403" dur="00:00:05.00"><span tts:color="#ededed" tts:textAlign="center"> Going to the cinema with your mates <br/> is fun, but it can be </span></p>
<p begin = "00:00:44.723" dur="00:00:05.00"><span tts:color="#ededed" tts:textAlign="center"> Going to the cinema with your mates <br/> is fun, but it can be expensive. </span></p>
<p begin = "00:00:45.683" dur="00:00:05.00"><span tts:color="#ededed" tts:textAlign="center"> Going to the cinema with your mates <br/> is fun, but it can be expensive.  So </span></p>
<p begin = "00:00:45.923" dur="00:00:05.00"><span tts:color="#ededed" tts:textAlign="center"> is fun, but it can be expensive. So </span><br/></p>
<p begin = "00:00:45.923" dur="00:00:05.00"><span tts:color="#ededed" tts:textAlign="center"> is fun, but it can be expensive. So <br/> it's </span></p>
<p begin = "00:00:46.163" dur="00:00:05.00"><span tts:color="#ededed" tts:textAlign="center"> is fun, but it can be expensive. So <br/> it's hardly </span></p>
<p begin = "00:00:46.363" dur="00:00:05.00"><span tts:color="#ededed" tts:textAlign="center"> is fun, but it can be expensive. So <br/> it's hardly surprising </span></p>
<p begin = "00:00:46.603" dur="00:00:05.00"><span tts:color="#ededed" tts:textAlign="center"> is fun, but it can be expensive. So <br/> it's hardly surprising that </span></p>
<p begin = "00:00:46.843" dur="00:00:05.00"><span tts:color="#ededed" tts:textAlign="center"> is fun, but it can be expensive. So <br/> it's hardly surprising that a</span></p>
<p begin = "00:00:47.083" dur="00:00:05.00"><span tts:color="#ededed" tts:textAlign="center"> is fun, but it can be expensive. So <br/> it's hardly surprising that anew </span></p>
<p begin = "00:00:47.403" dur="00:00:05.00"><span tts:color="#ededed" tts:textAlign="center"> it's hardly surprising that a new </span><br/></p>
<p begin = "00:00:47.403" dur="00:00:05.00"><span tts:color="#ededed" tts:textAlign="center"> it's hardly surprising that a new <br/> club </span></p>
<p begin = "00:00:47.643" dur="00:00:05.00"><span tts:color="#ededed" tts:textAlign="center"> it's hardly surprising that a new <br/> club which </span></p>
<p begin = "00:00:47.883" dur="00:00:05.00"><span tts:color="#ededed" tts:textAlign="center"> it's hardly surprising that a new <br/> club which lets </span></p>
<p begin = "00:00:48.083" dur="00:00:05.00"><span tts:color="#ededed" tts:textAlign="center"> it's hardly surprising that a new <br/> club which lets schools </span></p>
<p begin = "00:00:48.363" dur="00:00:05.00"><span tts:color="#ededed" tts:textAlign="center"> it's hardly surprising that a new <br/> club which lets schools show </span></p>
<p begin = "00:00:48.683" dur="00:00:05.00"><span tts:color="#ededed" tts:textAlign="center"> it's hardly surprising that a new <br/> club which lets schools show films </span></p>
<p begin = "00:00:48.923" dur="00:00:05.00"><span tts:color="#ededed" tts:textAlign="center"> club which lets schools show films </span><br/></p>
<p begin = "00:00:48.923" dur="00:00:05.00"><span tts:color="#ededed" tts:textAlign="center"> club which lets schools show films <br/> for </span></p>
<p begin = "00:00:49.163" dur="00:00:05.00"><span tts:color="#ededed" tts:textAlign="center"> club which lets schools show films <br/> for free </span></p>
<p begin = "00:00:49.403" dur="00:00:05.00"><span tts:color="#ededed" tts:textAlign="center"> club which lets schools show films <br/> for free is </span></p>
<p begin = "00:00:49.603" dur="00:00:05.00"><span tts:color="#ededed" tts:textAlign="center"> club which lets schools show films <br/> for free is proving </span></p>
<p begin = "00:00:49.963" dur="00:00:05.00"><span tts:color="#ededed" tts:textAlign="center"> club which lets schools show films <br/> for free is proving popular. </span></p>
<p begin = "00:00:50.803" dur="00:00:05.00"><span tts:color="#ededed" tts:textAlign="center"> club which lets schools show films <br/> for free is proving popular.  A </span></p>
<p begin = "00:00:51.043" dur="00:00:05.00"><span tts:color="#ededed" tts:textAlign="center"> for free is proving popular. A </span><br/></p>
<p begin = "00:00:51.043" dur="00:00:05.00"><span tts:color="#ededed" tts:textAlign="center"> for free is proving popular. A <br/> thousand </span></p>
<p begin = "00:00:51.283" dur="00:00:05.00"><span tts:color="#ededed" tts:textAlign="center"> for free is proving popular. A <br/> thousand schools </span></p>
<p begin = "00:00:51.523" dur="00:00:05.00"><span tts:color="#ededed" tts:textAlign="center"> for free is proving popular. A <br/> thousand schools have </span></p>
<p begin = "00:00:51.763" dur="00:00:05.00"><span tts:color="#ededed" tts:textAlign="center"> for free is proving popular. A <br/> thousand schools have already </span></p>
<p begin = "00:00:52.083" dur="00:00:05.00"><span tts:color="#ededed" tts:textAlign="center"> thousand schools have already </span><br/></p>
<p begin = "00:00:52.083" dur="00:00:05.00"><span tts:color="#ededed" tts:textAlign="center"> thousand schools have already <br/> signed </span></p>
<p begin = "00:00:52.283" dur="00:00:05.00"><span tts:color="#ededed" tts:textAlign="center"> thousand schools have already <br/> signed up </span></p>
<p begin = "00:00:52.563" dur="00:00:05.00"><span tts:color="#ededed" tts:textAlign="center"> thousand schools have already <br/> signed up and </span></p>
<p begin = "00:00:52.763" dur="00:00:05.00"><span tts:color="#ededed" tts:textAlign="center"> thousand schools have already <br/> signed up and Film </span></p>
<p begin = "00:00:53.003" dur="00:00:05.00"><span tts:color="#ededed" tts:textAlign="center"> thousand schools have already <br/> signed up and Film Club </span></p>
<p begin = "00:00:53.243" dur="00:00:05.00"><span tts:color="#ededed" tts:textAlign="center"> thousand schools have already <br/> signed up and Film Club has </span></p>
<p begin = "00:00:53.603" dur="00:00:05.00"><span tts:color="#ededed" tts:textAlign="center"> thousand schools have already <br/> signed up and Film Club has only </span></p>
<p begin = "00:00:53.803" dur="00:00:05.00"><span tts:color="#ededed" tts:textAlign="center"> signed up and Film Club has only </span><br/></p>
<p begin = "00:00:53.803" dur="00:00:05.00"><span tts:color="#ededed" tts:textAlign="center"> signed up and Film Club has only <br/> just </span></p>
<p begin = "00:00:54.043" dur="00:00:05.00"><span tts:color="#ededed" tts:textAlign="center"> signed up and Film Club has only <br/> just launched. </span></p>
<p begin = "00:00:54.283" dur="00:00:05.00"><span tts:color="#ededed" tts:textAlign="center"> signed up and Film Club has only <br/> just launched.  I've </span></p>
<p begin = "00:00:54.523" dur="00:00:05.00"><span tts:color="#ededed" tts:textAlign="center"> signed up and Film Club has only <br/> just launched.  I've been </span></p>
<p begin = "00:00:54.843" dur="00:00:05.00"><span tts:color="#ededed" tts:textAlign="center"> signed up and Film Club has only <br/> just launched.  I've been to </span></p>
<p begin = "00:00:55.083" dur="00:00:05.00"><span tts:color="#ededed" tts:textAlign="center"> signed up and Film Club has only <br/> just launched.  I've been to meet </span></p>
<p begin = "00:00:55.283" dur="00:00:05.00"><span tts:color="#ededed" tts:textAlign="center"> just launched. I've been to meet </span><br/></p>
<p begin = "00:00:55.283" dur="00:00:05.00"><span tts:color="#ededed" tts:textAlign="center"> just launched. I've been to meet <br/> pupils </span></p>
<p begin = "00:00:55.523" dur="00:00:05.00"><span tts:color="#ededed" tts:textAlign="center"> just launched. I've been to meet <br/> pupils trying </span></p>
<p begin = "00:00:55.763" dur="00:00:05.00"><span tts:color="#ededed" tts:textAlign="center"> just launched. I've been to meet <br/> pupils trying out </span></p>
<p begin = "00:00:56.163" dur="00:00:05.00"><span tts:color="#ededed" tts:textAlign="center"> just launched. I've been to meet <br/> pupils trying out the </span></p>
<p begin = "00:00:56.403" dur="00:00:05.00"><span tts:color="#ededed" tts:textAlign="center"> just launched. I've been to meet <br/> pupils trying out the idea. </span></p>
<p begin = "00:00:59.450" dur="00:00:05.00"><span tts:color="#ededed" tts:textAlign="center"> pupils trying out the idea. </span><br/></p>
<p begin = "00:00:59.450" dur="00:00:05.00"><span tts:color="#ededed" tts:textAlign="center"> pupils trying out the idea. <br/> These </span></p>
<p begin = "00:01:00.570" dur="00:00:05.00"><span tts:color="#ededed" tts:textAlign="center"> pupils trying out the idea. <br/> These guys </span></p>
<p begin = "00:01:00.650" dur="00:00:05.00"><span tts:color="#ededed" tts:textAlign="center"> pupils trying out the idea. <br/> These guys are </span></p>
<p begin = "00:01:01.410" dur="00:00:05.00"><span tts:color="#ededed" tts:textAlign="center"> pupils trying out the idea. <br/> These guys are part </span></p>
<p begin = "00:01:01.490" dur="00:00:05.00"><span tts:color="#ededed" tts:textAlign="center"> pupils trying out the idea. <br/> These guys are part of </span></p>
<p begin = "00:01:01.730" dur="00:00:05.00"><span tts:color="#ededed" tts:textAlign="center"> pupils trying out the idea. <br/> These guys are part of Film </span></p>
<p begin = "00:01:01.930" dur="00:00:05.00"><span tts:color="#ededed" tts:textAlign="center"> pupils trying out the idea. <br/> These guys are part of Film Club, </span></p>
<p begin = "00:01:02.170" dur="00:00:05.00"><span tts:color="#ededed" tts:textAlign="center"> These guys are part of Film Club, </span><br/></p>
<p begin = "00:01:02.170" dur="00:00:05.00"><span tts:color="#ededed" tts:textAlign="center"> These guys are part of Film Club, <br/> which </span></p>
<p begin = "00:01:02.530" dur="00:00:05.00"><span tts:color="#ededed" tts:textAlign="center"> These guys are part of Film Club, <br/> which means </span></p>
<p begin = "00:01:03.490" dur="00:00:05.00"><span tts:color="#ededed" tts:textAlign="center"> These guys are part of Film Club, <br/> which means they </span></p>
<p begin = "00:01:03.730" dur="00:00:05.00"><span tts:color="#ededed" tts:textAlign="center"> These guys are part of Film Club, <br/> which means they get </span></p>
<p begin = "00:01:04.570" dur="00:00:05.00"><span tts:color="#ededed" tts:textAlign="center"> These guys are part of Film Club, <br/> which means they get to </span></p>
<p begin = "00:01:04.610" dur="00:00:05.00"><span tts:color="#ededed" tts:textAlign="center"> These guys are part of Film Club, <br/> which means they get to watch </span></p>
<p begin = "00:01:04.890" dur="00:00:05.00"><span tts:color="#ededed" tts:textAlign="center"> These guys are part of Film Club, <br/> which means they get to watch films </span></p>
<p begin = "00:01:05.090" dur="00:00:05.00"><span tts:color="#ededed" tts:textAlign="center"> which means they get to watch films </span><br/></p>
<p begin = "00:01:05.090" dur="00:00:05.00"><span tts:color="#ededed" tts:textAlign="center"> which means they get to watch films <br/> at </span></p>
<p begin = "00:01:07.040" dur="00:00:05.00"><span tts:color="#ededed" tts:textAlign="center"> which means they get to watch films <br/> at school </span></p>
<p begin = "00:01:07.240" dur="00:00:05.00"><span tts:color="#ededed" tts:textAlign="center"> which means they get to watch films <br/> at school and </span></p>
<p begin = "00:01:07.360" dur="00:00:05.00"><span tts:color="#ededed" tts:textAlign="center"> which means they get to watch films <br/> at school and her </span></p>
<p begin = "00:01:07.600" dur="00:00:05.00"><span tts:color="#ededed" tts:textAlign="center"> which means they get to watch films <br/> at school and her 60,000 </span></p>
<p begin = "00:01:07.840" dur="00:00:05.00"><span tts:color="#ededed" tts:textAlign="center"> which means they get to watch films <br/> at school and her 60,000 to </span></p>
<p begin = "00:01:08.040" dur="00:00:05.00"><span tts:color="#ededed" tts:textAlign="center"> which means they get to watch films <br/> at school and her 60,000 to choose </span></p>
<p begin = "00:01:08.160" dur="00:00:05.00"><span tts:color="#ededed" tts:textAlign="center"> at school and her 60,000 to choose </span><br/></p>
<p begin = "00:01:08.160" dur="00:00:05.00"><span tts:color="#ededed" tts:textAlign="center"> at school and her 60,000 to choose <br/> from! </span></p>
<p begin = "00:01:08.400" dur="00:00:05.00"><span tts:color="#ededed" tts:textAlign="center"> at school and her 60,000 to choose <br/> from! It's </span></p>
<p begin = "00:01:08.640" dur="00:00:05.00"><span tts:color="#ededed" tts:textAlign="center"> at school and her 60,000 to choose <br/> from! It's like </span></p>
<p begin = "00:01:09.000" dur="00:00:05.00"><span tts:color="#ededed" tts:textAlign="center"> at school and her 60,000 to choose <br/> from! It's like going </span></p>
<p begin = "00:01:09.200" dur="00:00:05.00"><span tts:color="#ededed" tts:textAlign="center"> at school and her 60,000 to choose <br/> from! It's like going to </span></p>
<p begin = "00:01:09.440" dur="00:00:05.00"><span tts:color="#ededed" tts:textAlign="center"> at school and her 60,000 to choose <br/> from! It's like going to the </span></p>
<p begin = "00:01:09.640" dur="00:00:05.00"><span tts:color="#ededed" tts:textAlign="center"> at school and her 60,000 to choose <br/> from! It's like going to the cinema </span></p>
<p begin = "00:01:10.120" dur="00:00:05.00"><span tts:color="#ededed" tts:textAlign="center"> from! It's like going to the cinema </span><br/></p>
<p begin = "00:01:10.120" dur="00:00:05.00"><span tts:color="#ededed" tts:textAlign="center"> from! It's like going to the cinema <br/> with </span></p>
<p begin = "00:01:10.360" dur="00:00:05.00"><span tts:color="#ededed" tts:textAlign="center"> from! It's like going to the cinema <br/> with your </span></p>
<p begin = "00:01:11.200" dur="00:00:05.00"><span tts:color="#ededed" tts:textAlign="center"> from! It's like going to the cinema <br/> with your mates </span></p>
<p begin = "00:01:11.440" dur="00:00:05.00"><span tts:color="#ededed" tts:textAlign="center"> from! It's like going to the cinema <br/> with your mates but </span></p>
<p begin = "00:01:11.640" dur="00:00:05.00"><span tts:color="#ededed" tts:textAlign="center"> from! It's like going to the cinema <br/> with your mates but for </span></p>
<p begin = "00:01:11.880" dur="00:00:05.00"><span tts:color="#ededed" tts:textAlign="center"> from! It's like going to the cinema <br/> with your mates but for three! </span></p>
<p begin = "00:01:16.191" dur="00:00:05.00"><span tts:color="#ededed" tts:textAlign="center"> with your mates but for three! </span><br/></p>
<p begin = "00:01:16.191" dur="00:00:05.00"><span tts:color="#ededed" tts:textAlign="center"> with your mates but for three! <br/> - </span></p>
<p begin = "00:01:16.431" dur="00:00:05.00"><span tts:color="#ededed" tts:textAlign="center"> with your mates but for three! <br/> - but </span></p>
<p begin = "00:01:16.551" dur="00:00:05.00"><span tts:color="#ededed" tts:textAlign="center"> with your mates but for three! <br/> - but for </span></p>
<p begin = "00:01:16.751" dur="00:00:05.00"><span tts:color="#ededed" tts:textAlign="center"> with your mates but for three! <br/> - but for free. </span></p>
<p begin = "00:01:20.108" dur="00:00:05.00"><span tts:color="#ededed" tts:textAlign="center"> - but for free. </span><br/></p>
<p begin = "00:01:20.108" dur="00:00:05.00"><span tts:color="#ededed" tts:textAlign="center"> - but for free. <br/> The </span></p>
<p begin = "00:01:20.348" dur="00:00:05.00"><span tts:color="#ededed" tts:textAlign="center"> - but for free. <br/> The says </span></p>
<p begin = "00:01:21.548" dur="00:00:05.00"><span tts:color="#ededed" tts:textAlign="center"> - but for free. <br/> The says one </span></p>
<p begin = "00:01:21.628" dur="00:00:05.00"><span tts:color="#ededed" tts:textAlign="center"> - but for free. <br/> The says one of </span></p>
<p begin = "00:01:21.868" dur="00:00:05.00"><span tts:color="#ededed" tts:textAlign="center"> - but for free. <br/> The says one of 1,000 </span></p>
<p begin = "00:01:22.108" dur="00:00:05.00"><span tts:color="#ededed" tts:textAlign="center"> - but for free. <br/> The says one of 1,000 schools </span></p>
<p begin = "00:01:22.348" dur="00:00:05.00"><span tts:color="#ededed" tts:textAlign="center"> - but for free. <br/> The says one of 1,000 schools that </span></p>
<p begin = "00:01:22.428" dur="00:00:05.00"><span tts:color="#ededed" tts:textAlign="center"> The says one of 1,000 schools that </span><br/></p>
<p begin = "00:01:22.428" dur="00:00:05.00"><span tts:color="#ededed" tts:textAlign="center"> The says one of 1,000 schools that <br/> have </span></p>
<p begin = "00:01:23.148" dur="00:00:05.00"><span tts:color="#ededed" tts:textAlign="center"> The says one of 1,000 schools that <br/> have already </span></p>
<p begin = "00:01:24.028" dur="00:00:05.00"><span tts:color="#ededed" tts:textAlign="center"> The says one of 1,000 schools that <br/> have already signed </span></p>
<p begin = "00:01:24.228" dur="00:00:05.00"><span tts:color="#ededed" tts:textAlign="center"> The says one of 1,000 schools that <br/> have already signed up </span></p>
<p begin = "00:01:24.468" dur="00:00:05.00"><span tts:color="#ededed" tts:textAlign="center"> The says one of 1,000 schools that <br/> have already signed up but </span></p>
<p begin = "00:01:24.708" dur="00:00:05.00"><span tts:color="#ededed" tts:textAlign="center"> The says one of 1,000 schools that <br/> have already signed up but in </span></p>
<p begin = "00:01:24.908" dur="00:00:05.00"><span tts:color="#ededed" tts:textAlign="center"> The says one of 1,000 schools that <br/> have already signed up but in three </span></p>
<p begin = "00:01:25.148" dur="00:00:05.00"><span tts:color="#ededed" tts:textAlign="center"> have already signed up but in three </span><br/></p>
<p begin = "00:01:25.148" dur="00:00:05.00"><span tts:color="#ededed" tts:textAlign="center"> have already signed up but in three <br/> years, </span></p>
<p begin = "00:01:25.388" dur="00:00:05.00"><span tts:color="#ededed" tts:textAlign="center"> have already signed up but in three <br/> years, it </span></p>
<p begin = "00:01:26.948" dur="00:00:05.00"><span tts:color="#ededed" tts:textAlign="center"> have already signed up but in three <br/> years, it could </span></p>
<p begin = "00:01:27.148" dur="00:00:05.00"><span tts:color="#ededed" tts:textAlign="center"> have already signed up but in three <br/> years, it could have </span></p>
<p begin = "00:01:27.388" dur="00:00:05.00"><span tts:color="#ededed" tts:textAlign="center"> have already signed up but in three <br/> years, it could have 7,000 </span></p>
<p begin = "00:01:27.588" dur="00:00:05.00"><span tts:color="#ededed" tts:textAlign="center"> have already signed up but in three <br/> years, it could have 7,000 members </span></p>
<p begin = "00:01:29.148" dur="00:00:05.00"><span tts:color="#ededed" tts:textAlign="center"> years, it could have 7,000 members </span><br/></p>
<p begin = "00:01:29.148" dur="00:00:05.00"><span tts:color="#ededed" tts:textAlign="center"> years, it could have 7,000 members <br/> - </span></p>
<p begin = "00:01:29.388" dur="00:00:05.00"><span tts:color="#ededed" tts:textAlign="center"> years, it could have 7,000 members <br/> - this </span></p>
<p begin = "00:01:29.628" dur="00:00:05.00"><span tts:color="#ededed" tts:textAlign="center"> years, it could have 7,000 members <br/> - this is. </span></p>
<p begin = "00:01:29.748" dur="00:00:05.00"><span tts:color="#ededed" tts:textAlign="center"> years, it could have 7,000 members <br/> - this is.  Some </span></p>
<p begin = "00:01:30.468" dur="00:00:05.00"><span tts:color="#ededed" tts:textAlign="center"> years, it could have 7,000 members <br/> - this is.  Some schools </span></p>
<p begin = "00:01:31.308" dur="00:00:05.00"><span tts:color="#ededed" tts:textAlign="center"> years, it could have 7,000 members <br/> - this is.  Some schools have </span></p>
<p begin = "00:01:31.508" dur="00:00:05.00"><span tts:color="#ededed" tts:textAlign="center"> years, it could have 7,000 members <br/> - this is.  Some schools have had </span></p>
<p begin = "00:01:31.748" dur="00:00:05.00"><span tts:color="#ededed" tts:textAlign="center"> - this is. Some schools have had </span><br/></p>
<p begin = "00:01:31.748" dur="00:00:05.00"><span tts:color="#ededed" tts:textAlign="center"> - this is. Some schools have had <br/> experts </span></p>
<p begin = "00:01:31.988" dur="00:00:05.00"><span tts:color="#ededed" tts:textAlign="center"> - this is. Some schools have had <br/> experts come </span></p>
<p begin = "00:01:32.188" dur="00:00:05.00"><span tts:color="#ededed" tts:textAlign="center"> - this is. Some schools have had <br/> experts come and </span></p>
<p begin = "00:01:32.428" dur="00:00:05.00"><span tts:color="#ededed" tts:textAlign="center"> - this is. Some schools have had <br/> experts come and teach </span></p>
<p begin = "00:01:33.028" dur="00:00:05.00"><span tts:color="#ededed" tts:textAlign="center"> - this is. Some schools have had <br/> experts come and teach them </span></p>
<p begin = "00:01:33.228" dur="00:00:05.00"><span tts:color="#ededed" tts:textAlign="center"> - this is. Some schools have had <br/> experts come and teach them behind </span></p>
<p begin = "00:01:33.348" dur="00:00:05.00"><span tts:color="#ededed" tts:textAlign="center"> experts come and teach them behind </span><br/></p>
<p begin = "00:01:33.348" dur="00:00:05.00"><span tts:color="#ededed" tts:textAlign="center"> experts come and teach them behind <br/> the </span></p>
<p begin = "00:01:34.068" dur="00:00:05.00"><span tts:color="#ededed" tts:textAlign="center"> experts come and teach them behind <br/> the scenes </span></p>
<p begin = "00:01:34.188" dur="00:00:05.00"><span tts:color="#ededed" tts:textAlign="center"> experts come and teach them behind <br/> the scenes secrets, </span></p>
<p begin = "00:01:35.649" dur="00:00:05.00"><span tts:color="#ededed" tts:textAlign="center"> experts come and teach them behind <br/> the scenes secrets, even </span></p>
<p begin = "00:01:35.769" dur="00:00:05.00"><span tts:color="#ededed" tts:textAlign="center"> experts come and teach them behind <br/> the scenes secrets, even how </span></p>
<p begin = "00:01:36.009" dur="00:00:05.00"><span tts:color="#ededed" tts:textAlign="center"> experts come and teach them behind <br/> the scenes secrets, even how to </span></p>
<p begin = "00:01:37.409" dur="00:00:05.00"><span tts:color="#ededed" tts:textAlign="center"> the scenes secrets, even how to </span><br/></p>
<p begin = "00:01:37.649" dur="00:00:05.00"><span tts:color="#ededed" tts:textAlign="center"> the scenes secrets, even how to <br/>blood </span></p>
<p begin = "00:01:37.889" dur="00:00:05.00"><span tts:color="#ededed" tts:textAlign="center"> the scenes secrets, even how to <br/>blood poor </span></p>
<p begin = "00:01:38.089" dur="00:00:05.00"><span tts:color="#ededed" tts:textAlign="center"> the scenes secrets, even how to <br/>blood poor stock </span></p>
<p begin = "00:01:38.329" dur="00:00:05.00"><span tts:color="#ededed" tts:textAlign="center"> the scenes secrets, even how to <br/>blood poor stock which </span></p>
<p begin = "00:01:38.569" dur="00:00:05.00"><span tts:color="#ededed" tts:textAlign="center"> the scenes secrets, even how to <br/>blood poor stock which seems </span></p>
<p begin = "00:01:39.169" dur="00:00:05.00"><span tts:color="#ededed" tts:textAlign="center"> make blood poor stock which seems </span><br/></p>
<p begin = "00:01:39.169" dur="00:00:05.00"><span tts:color="#ededed" tts:textAlign="center"> make blood poor stock which seems <br/> have </span></p>
<p begin = "00:01:39.369" dur="00:00:05.00"><span tts:color="#ededed" tts:textAlign="center"> make blood poor stock which seems <br/> have you </span></p>
<p begin = "00:01:39.609" dur="00:00:05.00"><span tts:color="#ededed" tts:textAlign="center"> make blood poor stock which seems <br/> have you film </span></p>
<p begin = "00:01:39.849" dur="00:00:05.00"><span tts:color="#ededed" tts:textAlign="center"> make blood poor stock which seems <br/> have you film - </span></p>
<p begin = "00:01:40.809" dur="00:00:05.00"><span tts:color="#ededed" tts:textAlign="center"> make blood poor stock which seems <br/> have you film - which </span></p>
<p begin = "00:01:41.129" dur="00:00:05.00"><span tts:color="#ededed" tts:textAlign="center"> make blood poor stock which seems <br/> have you film - which Wales </span></p>
<p begin = "00:01:41.369" dur="00:00:05.00"><span tts:color="#ededed" tts:textAlign="center"> make blood poor stock which seems <br/> have you film - which Wales have </span></p>
<p begin = "00:01:41.489" dur="00:00:05.00"><span tts:color="#ededed" tts:textAlign="center"> have you film - which Wales have </span><br/></p>
<p begin = "00:01:41.489" dur="00:00:05.00"><span tts:color="#ededed" tts:textAlign="center"> have you film - which Wales have <br/> you </span></p>
<p begin = "00:01:41.729" dur="00:00:05.00"><span tts:color="#ededed" tts:textAlign="center"> have you film - which Wales have <br/> you seen? </span></p>
<p begin = "00:01:43.169" dur="00:00:05.00"><span tts:color="#ededed" tts:textAlign="center"> have you film - which Wales have <br/> you seen?  I </span></p>
<p begin = "00:01:43.369" dur="00:00:05.00"><span tts:color="#ededed" tts:textAlign="center"> have you film - which Wales have <br/> you seen?  I have </span></p>
<p begin = "00:01:43.609" dur="00:00:05.00"><span tts:color="#ededed" tts:textAlign="center"> have you film - which Wales have <br/> you seen?  I have seen </span></p>
<p begin = "00:01:43.849" dur="00:00:05.00"><span tts:color="#ededed" tts:textAlign="center"> have you film - which Wales have <br/> you seen?  I have seen BT. </span></p>
<p begin = "00:01:44.449" dur="00:00:05.00"><span tts:color="#ededed" tts:textAlign="center"> have you film - which Wales have <br/> you seen?  I have seen BT.  A </span></p>
<p begin = "00:01:44.649" dur="00:00:05.00"><span tts:color="#ededed" tts:textAlign="center"> have you film - which Wales have <br/> you seen?  I have seen BT.  A why </span></p>
<p begin = "00:01:45.489" dur="00:00:05.00"><span tts:color="#ededed" tts:textAlign="center"> have you film - which Wales have <br/> you seen?  I have seen BT.  A why not </span></p>
<p begin = "00:01:45.729" dur="00:00:05.00"><span tts:color="#ededed" tts:textAlign="center"> you seen?</span><br/></p>
<p begin = "00:01:45.729" dur="00:00:05.00"><span tts:color="#ededed" tts:textAlign="center"> you seen?<br/> I have seen BT.</span></p>
<p begin = "00:01:45.729" dur="00:00:05.00"><span tts:color="#ededed" tts:textAlign="center"> A why not </span><br/></p>
<p begin = "00:01:45.729" dur="00:00:05.00"><span tts:color="#ededed" tts:textAlign="center"> A why not <br/> get </span></p>
<p begin = "00:01:45.849" dur="00:00:05.00"><span tts:color="#ededed" tts:textAlign="center"> A why not <br/> get the </span></p>
<p begin = "00:01:46.889" dur="00:00:05.00"><span tts:color="#ededed" tts:textAlign="center"> A why not <br/> get the DVD </span></p>
<p begin = "00:01:47.129" dur="00:00:05.00"><span tts:color="#ededed" tts:textAlign="center"> A why not <br/> get the DVD and </span></p>
<p begin = "00:01:47.369" dur="00:00:05.00"><span tts:color="#ededed" tts:textAlign="center"> A why not <br/> get the DVD and watch </span></p>
<p begin = "00:01:47.609" dur="00:00:05.00"><span tts:color="#ededed" tts:textAlign="center"> A why not <br/> get the DVD and watch them </span></p>
<p begin = "00:01:47.809" dur="00:00:05.00"><span tts:color="#ededed" tts:textAlign="center"> A why not <br/> get the DVD and watch them at </span></p>
<p begin = "00:01:47.929" dur="00:00:05.00"><span tts:color="#ededed" tts:textAlign="center"> A why not <br/> get the DVD and watch them at home? </span></p>
<p begin = "00:01:49.009" dur="00:00:05.00"><span tts:color="#ededed" tts:textAlign="center"> get the DVD and watch them at home? </span><br/></p>
<p begin = "00:01:49.009" dur="00:00:05.00"><span tts:color="#00ffff" tts:textAlign="center"> get the DVD and watch them at home? <br/> We </span></p>
<p begin = "00:01:49.209" dur="00:00:05.00"><span tts:color="#00ffff" tts:textAlign="center"> get the DVD and watch them at home? <br/> We have </span></p>
<p begin = "00:01:49.329" dur="00:00:05.00"><span tts:color="#00ffff" tts:textAlign="center"> get the DVD and watch them at home? <br/> We have a</span></p>
<p begin = "00:01:49.569" dur="00:00:05.00"><span tts:color="#00ffff" tts:textAlign="center"> get the DVD and watch them at home? <br/> We have abigger </span></p>
<p begin = "00:01:49.809" dur="00:00:05.00"><span tts:color="#00ffff" tts:textAlign="center"> get the DVD and watch them at home? <br/> We have abigger screen </span></p>
<p begin = "00:01:50.049" dur="00:00:05.00"><span tts:color="#00ffff" tts:textAlign="center"> get the DVD and watch them at home? <br/> We have abigger screen here. </span></p>
<p begin = "00:01:51.913" dur="00:00:05.00"><span tts:color="#00ffff" tts:textAlign="center"> get the DVD and watch them at home? <br/> We have abigger screen here.  At </span></p>
<p begin = "00:01:52.153" dur="00:00:05.00"><span tts:color="#00ffff" tts:textAlign="center"> We have a bigger screen here. At </span><br/></p>
<p begin = "00:01:52.153" dur="00:00:05.00"><span tts:color="#00ffff" tts:textAlign="center"> We have a bigger screen here. At <br/> home </span></p>
<p begin = "00:01:52.393" dur="00:00:05.00"><span tts:color="#00ffff" tts:textAlign="center"> We have a bigger screen here. At <br/> home you </span></p>
<p begin = "00:01:52.753" dur="00:00:05.00"><span tts:color="#00ffff" tts:textAlign="center"> We have a bigger screen here. At <br/> home you just </span></p>
<p begin = "00:01:52.993" dur="00:00:05.00"><span tts:color="#00ffff" tts:textAlign="center"> We have a bigger screen here. At <br/> home you just talk </span></p>
<p begin = "00:01:53.193" dur="00:00:05.00"><span tts:color="#00ffff" tts:textAlign="center"> We have a bigger screen here. At <br/> home you just talk to </span></p>
<p begin = "00:01:53.313" dur="00:00:05.00"><span tts:color="#00ffff" tts:textAlign="center"> We have a bigger screen here. At <br/> home you just talk to your </span></p>
<p begin = "00:01:53.633" dur="00:00:05.00"><span tts:color="#00ffff" tts:textAlign="center"> We have a bigger screen here. At <br/> home you just talk to your brother </span></p>
<p begin = "00:01:54.633" dur="00:00:05.00"><span tts:color="#00ffff" tts:textAlign="center"> home you just talk to your brother </span><br/></p>
<p begin = "00:01:54.633" dur="00:00:05.00"><span tts:color="#00ffff" tts:textAlign="center"> home you just talk to your brother <br/> but </span></p>
<p begin = "00:01:54.873" dur="00:00:05.00"><span tts:color="#00ffff" tts:textAlign="center"> home you just talk to your brother <br/> but EU </span></p>
<p begin = "00:01:55.073" dur="00:00:05.00"><span tts:color="#00ffff" tts:textAlign="center"> home you just talk to your brother <br/> but EU can </span></p>
<p begin = "00:01:55.313" dur="00:00:05.00"><span tts:color="#00ffff" tts:textAlign="center"> home you just talk to your brother <br/> but EU can talk </span></p>
<p begin = "00:01:55.553" dur="00:00:05.00"><span tts:color="#00ffff" tts:textAlign="center"> home you just talk to your brother <br/> but EU can talk to </span></p>
<p begin = "00:01:55.633" dur="00:00:05.00"><span tts:color="#00ffff" tts:textAlign="center"> home you just talk to your brother <br/> but EU can talk to all </span></p>
<p begin = "00:01:55.873" dur="00:00:05.00"><span tts:color="#00ffff" tts:textAlign="center"> home you just talk to your brother <br/> but EU can talk to all your </span></p>
<p begin = "00:01:56.113" dur="00:00:05.00"><span tts:color="#00ffff" tts:textAlign="center"> home you just talk to your brother <br/> but EU can talk to all your mates. </span></p>
<p begin = "00:01:57.153" dur="00:00:05.00"><span tts:color="#00ffff" tts:textAlign="center"> but EU can talk to all your mates. </span><br/></p>
<p begin = "00:01:57.153" dur="00:00:05.00"><span tts:color="#00ff00" tts:textAlign="center"> but EU can talk to all your mates. <br/> The </span></p>
<p begin = "00:01:57.433" dur="00:00:05.00"><span tts:color="#00ff00" tts:textAlign="center"> but EU can talk to all your mates. <br/> The you </span></p>
<p begin = "00:01:57.753" dur="00:00:05.00"><span tts:color="#00ff00" tts:textAlign="center"> but EU can talk to all your mates. <br/> The you get </span></p>
<p begin = "00:01:57.993" dur="00:00:05.00"><span tts:color="#00ff00" tts:textAlign="center"> but EU can talk to all your mates. <br/> The you get to </span></p>
<p begin = "00:01:58.313" dur="00:00:05.00"><span tts:color="#00ff00" tts:textAlign="center"> but EU can talk to all your mates. <br/> The you get to watch </span></p>
<p begin = "00:01:59.313" dur="00:00:05.00"><span tts:color="#00ff00" tts:textAlign="center"> but EU can talk to all your mates. <br/> The you get to watch loads </span></p>
<p begin = "00:01:59.393" dur="00:00:05.00"><span tts:color="#00ff00" tts:textAlign="center"> but EU can talk to all your mates. <br/> The you get to watch loads of </span></p>
<p begin = "00:01:59.633" dur="00:00:05.00"><span tts:color="#00ff00" tts:textAlign="center"> but EU can talk to all your mates. <br/> The you get to watch loads of films </span></p>
<p begin = "00:01:59.833" dur="00:00:05.00"><span tts:color="#00ff00" tts:textAlign="center"> The you get to watch loads of films </span><br/></p>
<p begin = "00:01:59.833" dur="00:00:05.00"><span tts:color="#00ff00" tts:textAlign="center"> The you get to watch loads of films <br/> and </span></p>
<p begin = "00:02:00.113" dur="00:00:05.00"><span tts:color="#00ff00" tts:textAlign="center"> The you get to watch loads of films <br/> and see </span></p>
<p begin = "00:02:00.193" dur="00:00:05.00"><span tts:color="#00ff00" tts:textAlign="center"> The you get to watch loads of films <br/> and see your </span></p>
<p begin = "00:02:00.473" dur="00:00:05.00"><span tts:color="#00ff00" tts:textAlign="center"> The you get to watch loads of films <br/> and see your friends. </span></p>
<p begin = "00:02:01.513" dur="00:00:05.00"><span tts:color="#00ff00" tts:textAlign="center"> The you get to watch loads of films <br/> and see your friends.  But </span></p>
<p begin = "00:02:01.753" dur="00:00:05.00"><span tts:color="#00ff00" tts:textAlign="center"> The you get to watch loads of films <br/> and see your friends.  But you </span></p>
<p begin = "00:02:01.953" dur="00:00:05.00"><span tts:color="#00ff00" tts:textAlign="center"> The you get to watch loads of films <br/> and see your friends.  But you see </span></p>
<p begin = "00:02:03.033" dur="00:00:05.00"><span tts:color="#00ff00" tts:textAlign="center"> and see your friends.</span><br/></p>
<p begin = "00:02:03.033" dur="00:00:05.00"><span tts:color="#00ff00" tts:textAlign="center"> and see your friends.<br/> But you see </span></p>
<p begin = "00:02:03.033" dur="00:00:05.00"><span tts:color="#ededed" tts:textAlign="center"> them </span><br/></p>
<p begin = "00:02:04.113" dur="00:00:05.00"><span tts:color="#ededed" tts:textAlign="center"> them <br/>at </span></p>
<p begin = "00:02:04.353" dur="00:00:05.00"><span tts:color="#ededed" tts:textAlign="center"> them <br/>at school </span></p>
<p begin = "00:02:04.433" dur="00:00:05.00"><span tts:color="#ededed" tts:textAlign="center"> them <br/>at school all </span></p>
<p begin = "00:02:04.713" dur="00:00:05.00"><span tts:color="#ededed" tts:textAlign="center"> them <br/>at school all day. </span></p>
<p begin = "00:02:04.913" dur="00:00:05.00"><span tts:color="#ededed" tts:textAlign="center"> them <br/>at school all day.  Do </span></p>
<p begin = "00:02:05.153" dur="00:00:05.00"><span tts:color="#ededed" tts:textAlign="center"> them <br/>at school all day.  Do you </span></p>
<p begin = "00:02:05.233" dur="00:00:05.00"><span tts:color="#ededed" tts:textAlign="center"> them <br/>at school all day.  Do you want </span></p>
<p begin = "00:02:05.473" dur="00:00:05.00"><span tts:color="#ededed" tts:textAlign="center"> them at school all day. Do you want </span><br/></p>
<p begin = "00:02:05.473" dur="00:00:05.00"><span tts:color="#ededed" tts:textAlign="center"> them at school all day. Do you want <br/> to </span></p>
<p begin = "00:02:05.713" dur="00:00:05.00"><span tts:color="#ededed" tts:textAlign="center"> them at school all day. Do you want <br/> to see </span></p>
<p begin = "00:02:05.953" dur="00:00:05.00"><span tts:color="#ededed" tts:textAlign="center"> them at school all day. Do you want <br/> to see them </span></p>
<p begin = "00:02:06.033" dur="00:00:05.00"><span tts:color="#ededed" tts:textAlign="center"> them at school all day. Do you want <br/> to see them after? </span></p>
<p begin = "00:02:06.873" dur="00:00:05.00"><span tts:color="#ededed" tts:textAlign="center"> them at school all day. Do you want <br/> to see them after?  Yes. </span></p>
<p begin = "00:02:08.233" dur="00:00:05.00"><span tts:color="#ededed" tts:textAlign="center"> them at school all day. Do you want <br/> to see them after?  Yes.  It </span></p>
<p begin = "00:02:08.793" dur="00:00:05.00"><span tts:color="#ededed" tts:textAlign="center"> them at school all day. Do you want <br/> to see them after?  Yes.  It gives </span></p>
<p begin = "00:02:09.153" dur="00:00:05.00"><span tts:color="#ededed" tts:textAlign="center"> to see them after?</span><br/></p>
<p begin = "00:02:09.153" dur="00:00:05.00"><span tts:color="#ededed" tts:textAlign="center"> to see them after?<br/> Yes.</span></p>
<p begin = "00:02:09.153" dur="00:00:05.00"><span tts:color="#ededed" tts:textAlign="center"> It gives </span><br/></p>
<p begin = "00:02:09.153" dur="00:00:05.00"><span tts:color="#fefe00" tts:textAlign="center"> It gives <br/> people </span></p>
<p begin = "00:02:09.713" dur="00:00:05.00"><span tts:color="#fefe00" tts:textAlign="center"> It gives <br/> people opportunities </span></p>
<p begin = "00:02:09.953" dur="00:00:05.00"><span tts:color="#fefe00" tts:textAlign="center"> It gives <br/> people opportunities to </span></p>
<p begin = "00:02:10.193" dur="00:00:05.00"><span tts:color="#fefe00" tts:textAlign="center"> It gives <br/> people opportunities to see </span></p>
<p begin = "00:02:10.913" dur="00:00:05.00"><span tts:color="#fefe00" tts:textAlign="center"> It gives <br/> people opportunities to see films </span></p>
<p begin = "00:02:11.113" dur="00:00:05.00"><span tts:color="#fefe00" tts:textAlign="center"> people opportunities to see films </span><br/></p>
<p begin = "00:02:11.113" dur="00:00:05.00"><span tts:color="#fefe00" tts:textAlign="center"> people opportunities to see films <br/> they </span></p>
<p begin = "00:02:11.353" dur="00:00:05.00"><span tts:color="#fefe00" tts:textAlign="center"> people opportunities to see films <br/> they haven't </span></p>
<p begin = "00:02:11.473" dur="00:00:05.00"><span tts:color="#fefe00" tts:textAlign="center"> people opportunities to see films <br/> they haven't seen </span></p>
<p begin = "00:02:11.713" dur="00:00:05.00"><span tts:color="#fefe00" tts:textAlign="center"> people opportunities to see films <br/> they haven't seen before. </span></p>
<p begin = "00:02:13.153" dur="00:00:05.00"><span tts:color="#fefe00" tts:textAlign="center"> people opportunities to see films <br/> they haven't seen before.  I </span></p>
<p begin = "00:02:13.393" dur="00:00:05.00"><span tts:color="#fefe00" tts:textAlign="center"> people opportunities to see films <br/> they haven't seen before.  I had </span></p>
<p begin = "00:02:13.593" dur="00:00:05.00"><span tts:color="#fefe00" tts:textAlign="center"> people opportunities to see films <br/> they haven't seen before.  I had to </span></p>
<p begin = "00:02:14.193" dur="00:00:05.00"><span tts:color="#fefe00" tts:textAlign="center"> they haven't seen before.</span><br/></p>
<p begin = "00:02:14.193" dur="00:00:05.00"><span tts:color="#fefe00" tts:textAlign="center"> they haven't seen before.<br/> I had to </span></p>
<p begin = "00:02:14.193" dur="00:00:05.00"><span tts:color="#ededed" tts:textAlign="center"> take </span><br/></p>
<p begin = "00:02:14.273" dur="00:00:05.00"><span tts:color="#ededed" tts:textAlign="center"> take <br/>my </span></p>
<p begin = "00:02:14.513" dur="00:00:05.00"><span tts:color="#ededed" tts:textAlign="center"> take <br/>my own </span></p>
<p begin = "00:02:14.753" dur="00:00:05.00"><span tts:color="#ededed" tts:textAlign="center"> take <br/>my own popcorn! </span></p>
<p begin = "00:02:15.913" dur="00:00:05.00"><span tts:color="#ededed" tts:textAlign="center"> take my own popcorn! </span><br/></p>
<p begin = "00:02:15.913" dur="00:00:05.00"><span tts:color="#ededed" tts:textAlign="center"> take my own popcorn! <br/> The </span></p>
<p begin = "00:02:16.193" dur="00:00:05.00"><span tts:color="#ededed" tts:textAlign="center"> take my own popcorn! <br/> The slots </span></p>
<p begin = "00:02:16.393" dur="00:00:05.00"><span tts:color="#ededed" tts:textAlign="center"> take my own popcorn! <br/> The slots in </span></p>
<p begin = "00:02:16.633" dur="00:00:05.00"><span tts:color="#ededed" tts:textAlign="center"> take my own popcorn! <br/> The slots in the </span></p>
<p begin = "00:02:16.993" dur="00:00:05.00"><span tts:color="#ededed" tts:textAlign="center"> take my own popcorn! <br/> The slots in the quarter-finals </span></p>
<p begin = "00:02:17.233" dur="00:00:05.00"><span tts:color="#ededed" tts:textAlign="center"> take my own popcorn! <br/> The slots in the quarter-finals of </span></p>
<p begin = "00:02:17.433" dur="00:00:05.00"><span tts:color="#ededed" tts:textAlign="center"> The slots in the quarter-finals of </span><br/></p>
<p begin = "00:02:17.433" dur="00:00:05.00"><span tts:color="#ededed" tts:textAlign="center"> The slots in the quarter-finals of <br/> Euro </span></p>
<p begin = "00:02:17.713" dur="00:00:05.00"><span tts:color="#ededed" tts:textAlign="center"> The slots in the quarter-finals of <br/> Euro 2008 </span></p>
<p begin = "00:02:17.953" dur="00:00:05.00"><span tts:color="#ededed" tts:textAlign="center"> The slots in the quarter-finals of <br/> Euro 2008 are </span></p>
<p begin = "00:02:18.233" dur="00:00:05.00"><span tts:color="#ededed" tts:textAlign="center"> The slots in the quarter-finals of <br/> Euro 2008 are filling </span></p>
<p begin = "00:02:18.513" dur="00:00:05.00"><span tts:color="#ededed" tts:textAlign="center"> The slots in the quarter-finals of <br/> Euro 2008 are filling up. </span></p>
<p begin = "00:02:20.193" dur="00:00:05.00"><span tts:color="#ededed" tts:textAlign="center"> The slots in the quarter-finals of <br/> Euro 2008 are filling up.  Germany </span></p>
<p begin = "00:02:20.393" dur="00:00:05.00"><span tts:color="#ededed" tts:textAlign="center"> Euro 2008 are filling up. Germany </span><br/></p>
<p begin = "00:02:20.393" dur="00:00:05.00"><span tts:color="#ededed" tts:textAlign="center"> Euro 2008 are filling up. Germany <br/> made </span></p>
<p begin = "00:02:20.633" dur="00:00:05.00"><span tts:color="#ededed" tts:textAlign="center"> Euro 2008 are filling up. Germany <br/> made it </span></p>
<p begin = "00:02:20.873" dur="00:00:05.00"><span tts:color="#ededed" tts:textAlign="center"> Euro 2008 are filling up. Germany <br/> made it to </span></p>
<p begin = "00:02:21.113" dur="00:00:05.00"><span tts:color="#ededed" tts:textAlign="center"> Euro 2008 are filling up. Germany <br/> made it to the </span></p>
<p begin = "00:02:21.353" dur="00:00:05.00"><span tts:color="#ededed" tts:textAlign="center"> Euro 2008 are filling up. Germany <br/> made it to the knock </span></p>
<p begin = "00:02:21.713" dur="00:00:05.00"><span tts:color="#ededed" tts:textAlign="center"> Euro 2008 are filling up. Germany <br/> made it to the knock out </span></p>
<p begin = "00:02:21.913" dur="00:00:05.00"><span tts:color="#ededed" tts:textAlign="center"> Euro 2008 are filling up. Germany <br/> made it to the knock out stages </span></p>
<p begin = "00:02:22.153" dur="00:00:05.00"><span tts:color="#ededed" tts:textAlign="center"> Euro 2008 are filling up. Germany <br/> made it to the knock out stages of </span></p>
<p begin = "00:02:22.393" dur="00:00:05.00"><span tts:color="#ededed" tts:textAlign="center"> made it to the knock out stages of </span><br/></p>
<p begin = "00:02:22.393" dur="00:00:05.00"><span tts:color="#ededed" tts:textAlign="center"> made it to the knock out stages of <br/> the </span></p>
<p begin = "00:02:22.593" dur="00:00:05.00"><span tts:color="#ededed" tts:textAlign="center"> made it to the knock out stages of <br/> the competition </span></p>
<p begin = "00:02:22.833" dur="00:00:05.00"><span tts:color="#ededed" tts:textAlign="center"> made it to the knock out stages of <br/> the competition last </span></p>
<p begin = "00:02:23.193" dur="00:00:05.00"><span tts:color="#ededed" tts:textAlign="center"> made it to the knock out stages of <br/> the competition last night. </span></p>
<p begin = "00:02:23.433" dur="00:00:05.00"><span tts:color="#ededed" tts:textAlign="center"> made it to the knock out stages of <br/> the competition last night.  They </span></p>
<p begin = "00:02:23.633" dur="00:00:05.00"><span tts:color="#ededed" tts:textAlign="center"> the competition last night. They </span><br/></p>
<p begin = "00:02:23.633" dur="00:00:05.00"><span tts:color="#ededed" tts:textAlign="center"> the competition last night. They <br/> beat </span></p>
<p begin = "00:02:23.873" dur="00:00:05.00"><span tts:color="#ededed" tts:textAlign="center"> the competition last night. They <br/> beat Austria </span></p>
<p begin = "00:02:24.113" dur="00:00:05.00"><span tts:color="#ededed" tts:textAlign="center"> the competition last night. They <br/> beat Austria 1-0, </span></p>
<p begin = "00:02:24.433" dur="00:00:05.00"><span tts:color="#ededed" tts:textAlign="center"> the competition last night. They <br/> beat Austria 1-0, confirming </span></p>
<p begin = "00:02:24.713" dur="00:00:05.00"><span tts:color="#ededed" tts:textAlign="center"> the competition last night. They <br/> beat Austria 1-0, confirming the </span></p>
<p begin = "00:02:24.913" dur="00:00:05.00"><span tts:color="#ededed" tts:textAlign="center"> beat Austria 1-0, confirming the </span><br/></p>
<p begin = "00:02:24.913" dur="00:00:05.00"><span tts:color="#ededed" tts:textAlign="center"> beat Austria 1-0, confirming the <br/> co-hosts' </span></p>
<p begin = "00:02:25.153" dur="00:00:05.00"><span tts:color="#ededed" tts:textAlign="center"> beat Austria 1-0, confirming the <br/> co-hosts' exit </span></p>
<p begin = "00:02:25.393" dur="00:00:05.00"><span tts:color="#ededed" tts:textAlign="center"> beat Austria 1-0, confirming the <br/> co-hosts' exit from </span></p>
<p begin = "00:02:25.633" dur="00:00:05.00"><span tts:color="#ededed" tts:textAlign="center"> beat Austria 1-0, confirming the <br/> co-hosts' exit from the </span></p>
<p begin = "00:02:25.953" dur="00:00:05.00"><span tts:color="#ededed" tts:textAlign="center"> beat Austria 1-0, confirming the <br/> co-hosts' exit from the tournament. </span></p>
<p begin = "00:02:26.193" dur="00:00:05.00"><span tts:color="#ededed" tts:textAlign="center"> co-hosts' exit from the tournament. </span><br/></p>
<p begin = "00:02:26.193" dur="00:00:05.00"><span tts:color="#ededed" tts:textAlign="center"> co-hosts' exit from the tournament. <br/> Germany </span></p>
<p begin = "00:02:26.433" dur="00:00:05.00"><span tts:color="#ededed" tts:textAlign="center"> co-hosts' exit from the tournament. <br/> Germany go </span></p>
<p begin = "00:02:26.673" dur="00:00:05.00"><span tts:color="#ededed" tts:textAlign="center"> co-hosts' exit from the tournament. <br/> Germany go on </span></p>
<p begin = "00:02:26.873" dur="00:00:05.00"><span tts:color="#ededed" tts:textAlign="center"> co-hosts' exit from the tournament. <br/> Germany go on to </span></p>
<p begin = "00:02:27.233" dur="00:00:05.00"><span tts:color="#ededed" tts:textAlign="center"> co-hosts' exit from the tournament. <br/> Germany go on to play </span></p>
<p begin = "00:02:27.473" dur="00:00:05.00"><span tts:color="#ededed" tts:textAlign="center"> co-hosts' exit from the tournament. <br/> Germany go on to play Portugal </span></p>
<p begin = "00:02:27.713" dur="00:00:05.00"><span tts:color="#ededed" tts:textAlign="center"> co-hosts' exit from the tournament. <br/> Germany go on to play Portugal in </span></p>
<p begin = "00:02:27.913" dur="00:00:05.00"><span tts:color="#ededed" tts:textAlign="center"> Germany go on to play Portugal in </span><br/></p>
<p begin = "00:02:27.913" dur="00:00:05.00"><span tts:color="#ededed" tts:textAlign="center"> Germany go on to play Portugal in <br/> the </span></p>
<p begin = "00:02:28.153" dur="00:00:05.00"><span tts:color="#ededed" tts:textAlign="center"> Germany go on to play Portugal in <br/> the quarter-finals. </span></p>
<p begin = "00:02:28.993" dur="00:00:05.00"><span tts:color="#ededed" tts:textAlign="center"> Germany go on to play Portugal in <br/> the quarter-finals.  Chelsea </span></p>
<p begin = "00:02:29.193" dur="00:00:05.00"><span tts:color="#ededed" tts:textAlign="center"> the quarter-finals. Chelsea </span><br/></p>
<p begin = "00:02:29.193" dur="00:00:05.00"><span tts:color="#ededed" tts:textAlign="center"> the quarter-finals. Chelsea <br/> midfielder </span></p>
<p begin = "00:02:29.433" dur="00:00:05.00"><span tts:color="#ededed" tts:textAlign="center"> the quarter-finals. Chelsea <br/> midfielder Michael </span></p>
<p begin = "00:02:29.713" dur="00:00:05.00"><span tts:color="#ededed" tts:textAlign="center"> the quarter-finals. Chelsea <br/> midfielder Michael Ballack </span></p>
<p begin = "00:02:30.033" dur="00:00:05.00"><span tts:color="#ededed" tts:textAlign="center"> the quarter-finals. Chelsea <br/> midfielder Michael Ballack scored </span></p>
<p begin = "00:02:30.273" dur="00:00:05.00"><span tts:color="#ededed" tts:textAlign="center"> midfielder Michael Ballack scored </span><br/></p>
<p begin = "00:02:30.273" dur="00:00:05.00"><span tts:color="#ededed" tts:textAlign="center"> midfielder Michael Ballack scored <br/> the </span></p>
<p begin = "00:02:30.473" dur="00:00:05.00"><span tts:color="#ededed" tts:textAlign="center"> midfielder Michael Ballack scored <br/> the only </span></p>
<p begin = "00:02:30.713" dur="00:00:05.00"><span tts:color="#ededed" tts:textAlign="center"> midfielder Michael Ballack scored <br/> the only goal </span></p>
<p begin = "00:02:30.953" dur="00:00:05.00"><span tts:color="#ededed" tts:textAlign="center"> midfielder Michael Ballack scored <br/> the only goal of </span></p>
<p begin = "00:02:31.313" dur="00:00:05.00"><span tts:color="#ededed" tts:textAlign="center"> midfielder Michael Ballack scored <br/> the only goal of the </span></p>
<p begin = "00:02:31.553" dur="00:00:05.00"><span tts:color="#ededed" tts:textAlign="center"> midfielder Michael Ballack scored <br/> the only goal of the game. </span></p>
<p begin = "00:02:31.753" dur="00:00:05.00"><span tts:color="#ededed" tts:textAlign="center"> midfielder Michael Ballack scored <br/> the only goal of the game.  He </span></p>
<p begin = "00:02:31.993" dur="00:00:05.00"><span tts:color="#ededed" tts:textAlign="center"> midfielder Michael Ballack scored <br/> the only goal of the game.  He knows </span></p>
<p begin = "00:02:32.353" dur="00:00:05.00"><span tts:color="#ededed" tts:textAlign="center"> the only goal of the game. He knows </span><br/></p>
<p begin = "00:02:32.353" dur="00:00:05.00"><span tts:color="#ededed" tts:textAlign="center"> the only goal of the game. He knows <br/> they're </span></p>
<p begin = "00:02:32.553" dur="00:00:05.00"><span tts:color="#ededed" tts:textAlign="center"> the only goal of the game. He knows <br/> they're favourite </span></p>
<p begin = "00:02:32.793" dur="00:00:05.00"><span tts:color="#ededed" tts:textAlign="center"> the only goal of the game. He knows <br/> they're favourite to </span></p>
<p begin = "00:02:33.033" dur="00:00:05.00"><span tts:color="#ededed" tts:textAlign="center"> the only goal of the game. He knows <br/> they're favourite to win </span></p>
<p begin = "00:02:33.233" dur="00:00:05.00"><span tts:color="#ededed" tts:textAlign="center"> the only goal of the game. He knows <br/> they're favourite to win the </span></p>
<p begin = "00:02:33.513" dur="00:00:05.00"><span tts:color="#ededed" tts:textAlign="center"> they're favourite to win the </span><br/></p>
<p begin = "00:02:33.513" dur="00:00:05.00"><span tts:color="#ededed" tts:textAlign="center"> they're favourite to win the <br/> competition </span></p>
<p begin = "00:02:33.833" dur="00:00:05.00"><span tts:color="#ededed" tts:textAlign="center"> they're favourite to win the <br/> competition and </span></p>
<p begin = "00:02:34.073" dur="00:00:05.00"><span tts:color="#ededed" tts:textAlign="center"> they're favourite to win the <br/> competition and is </span></p>
<p begin = "00:02:34.273" dur="00:00:05.00"><span tts:color="#ededed" tts:textAlign="center"> they're favourite to win the <br/> competition and is concentrating </span></p>
<p begin = "00:02:34.553" dur="00:00:05.00"><span tts:color="#ededed" tts:textAlign="center"> they're favourite to win the <br/> competition and is concentrating on </span></p>
<p begin = "00:02:34.753" dur="00:00:05.00"><span tts:color="#ededed" tts:textAlign="center"> competition and is concentrating on </span><br/></p>
<p begin = "00:02:34.753" dur="00:00:05.00"><span tts:color="#ededed" tts:textAlign="center"> competition and is concentrating on <br/> getting </span></p>
<p begin = "00:02:35.113" dur="00:00:05.00"><span tts:color="#ededed" tts:textAlign="center"> competition and is concentrating on <br/> getting there. </span></p>
<p begin = "00:02:39.784" dur="00:00:05.00"><span tts:color="#ededed" tts:textAlign="center"> getting there. </span><br/></p>
<p begin = "00:02:39.784" dur="00:00:05.00"><span tts:color="#fefe00" tts:textAlign="center"> getting there. <br/> We </span></p>
<p begin = "00:02:40.024" dur="00:00:05.00"><span tts:color="#fefe00" tts:textAlign="center"> getting there. <br/> We have </span></p>
<p begin = "00:02:40.224" dur="00:00:05.00"><span tts:color="#fefe00" tts:textAlign="center"> getting there. <br/> We have a</span></p>
<p begin = "00:02:40.464" dur="00:00:05.00"><span tts:color="#fefe00" tts:textAlign="center"> getting there. <br/> We have abig </span></p>
<p begin = "00:02:40.584" dur="00:00:05.00"><span tts:color="#fefe00" tts:textAlign="center"> getting there. <br/> We have abig target, </span></p>
<p begin = "00:02:40.824" dur="00:00:05.00"><span tts:color="#fefe00" tts:textAlign="center"> getting there. <br/> We have abig target, be </span></p>
<p begin = "00:02:41.304" dur="00:00:05.00"><span tts:color="#fefe00" tts:textAlign="center"> getting there. <br/> We have abig target, be want </span></p>
<p begin = "00:02:41.504" dur="00:00:05.00"><span tts:color="#fefe00" tts:textAlign="center"> getting there. <br/> We have abig target, be want to </span></p>
<p begin = "00:02:41.864" dur="00:00:05.00"><span tts:color="#fefe00" tts:textAlign="center"> getting there. <br/> We have abig target, be want to go </span></p>
<p begin = "00:02:42.064" dur="00:00:05.00"><span tts:color="#fefe00" tts:textAlign="center"> We have a big target, be want to go </span><br/></p>
<p begin = "00:02:42.064" dur="00:00:05.00"><span tts:color="#fefe00" tts:textAlign="center"> We have a big target, be want to go <br/> to </span></p>
<p begin = "00:02:42.304" dur="00:00:05.00"><span tts:color="#fefe00" tts:textAlign="center"> We have a big target, be want to go <br/> to the </span></p>
<p begin = "00:02:42.424" dur="00:00:05.00"><span tts:color="#fefe00" tts:textAlign="center"> We have a big target, be want to go <br/> to the final </span></p>
<p begin = "00:02:42.624" dur="00:00:05.00"><span tts:color="#fefe00" tts:textAlign="center"> We have a big target, be want to go <br/> to the final and </span></p>
<p begin = "00:02:43.144" dur="00:00:05.00"><span tts:color="#fefe00" tts:textAlign="center"> We have a big target, be want to go <br/> to the final and this </span></p>
<p begin = "00:02:43.224" dur="00:00:05.00"><span tts:color="#fefe00" tts:textAlign="center"> We have a big target, be want to go <br/> to the final and this was </span></p>
<p begin = "00:02:43.464" dur="00:00:05.00"><span tts:color="#fefe00" tts:textAlign="center"> We have a big target, be want to go <br/> to the final and this was a</span></p>
<p begin = "00:02:43.704" dur="00:00:05.00"><span tts:color="#fefe00" tts:textAlign="center"> We have a big target, be want to go <br/> to the final and this was avery </span></p>
<p begin = "00:02:44.064" dur="00:00:05.00"><span tts:color="#fefe00" tts:textAlign="center"> to the final and this was a very </span><br/></p>
<p begin = "00:02:44.064" dur="00:00:05.00"><span tts:color="#fefe00" tts:textAlign="center"> to the final and this was a very <br/> important </span></p>
<p begin = "00:02:44.304" dur="00:00:05.00"><span tts:color="#fefe00" tts:textAlign="center"> to the final and this was a very <br/> important victory </span></p>
<p begin = "00:02:44.504" dur="00:00:05.00"><span tts:color="#fefe00" tts:textAlign="center"> to the final and this was a very <br/> important victory today. </span></p>
<p begin = "00:02:47.378" dur="00:00:05.00"><span tts:color="#fefe00" tts:textAlign="center"> to the final and this was a very <br/> important victory today.  I </span></p>
<p begin = "00:02:47.618" dur="00:00:05.00"><span tts:color="#fefe00" tts:textAlign="center"> to the final and this was a very <br/> important victory today.  I will </span></p>
<p begin = "00:02:48.098" dur="00:00:05.00"><span tts:color="#fefe00" tts:textAlign="center"> to the final and this was a very <br/> important victory today.  I will be </span></p>
<p begin = "00:02:48.178" dur="00:00:05.00"><span tts:color="#fefe00" tts:textAlign="center"> important victory today.</span><br/></p>
<p begin = "00:02:48.178" dur="00:00:05.00"><span tts:color="#fefe00" tts:textAlign="center"> important victory today.<br/> I will be </span></p>
<p begin = "00:02:48.178" dur="00:00:05.00"><span tts:color="#ededed" tts:textAlign="center"> back </span><br/></p>
<p begin = "00:02:48.418" dur="00:00:05.00"><span tts:color="#ededed" tts:textAlign="center"> back <br/>with </span></p>
<p begin = "00:02:48.778" dur="00:00:05.00"><span tts:color="#ededed" tts:textAlign="center"> back <br/>with your </span></p>
<p begin = "00:02:49.618" dur="00:00:05.00"><span tts:color="#ededed" tts:textAlign="center"> back <br/>with your next </span></p>
<p begin = "00:02:51.448" dur="00:00:05.00"><span tts:color="#ededed" tts:textAlign="center"> back <br/>with your next update </span></p>
<p begin = "00:02:51.648" dur="00:00:05.00"><span tts:color="#ededed" tts:textAlign="center"> back <br/>with your next update in </span></p>
<p begin = "00:02:51.888" dur="00:00:05.00"><span tts:color="#ededed" tts:textAlign="center"> back <br/>with your next update in one </span></p>
<p begin = "00:02:52.088" dur="00:00:05.00"><span tts:color="#ededed" tts:textAlign="center"> back with your next update in one </span><br/></p>
<p begin = "00:02:52.088" dur="00:00:05.00"><span tts:color="#ededed" tts:textAlign="center"> back with your next update in one <br/> hour </span></p>
<p begin = "00:02:52.248" dur="00:00:05.00"><span tts:color="#ededed" tts:textAlign="center"> back with your next update in one <br/> hour on </span></p>
<p begin = "00:02:52.488" dur="00:00:05.00"><span tts:color="#ededed" tts:textAlign="center"> back with your next update in one <br/> hour on CBBC. </span></p>
<p begin = "00:02:52.728" dur="00:00:05.00"><span tts:color="#ededed" tts:textAlign="center"> back with your next update in one <br/> hour on CBBC.  Until </span></p>
<p begin = "00:02:52.928" dur="00:00:05.00"><span tts:color="#ededed" tts:textAlign="center"> back with your next update in one <br/> hour on CBBC.  Until then </span></p>
<p begin = "00:02:53.048" dur="00:00:05.00"><span tts:color="#ededed" tts:textAlign="center"> back with your next update in one <br/> hour on CBBC.  Until then you </span></p>
<p begin = "00:02:53.248" dur="00:00:05.00"><span tts:color="#ededed" tts:textAlign="center"> back with your next update in one <br/> hour on CBBC.  Until then you can </span></p>
<p begin = "00:02:53.608" dur="00:00:05.00"><span tts:color="#ededed" tts:textAlign="center"> hour on CBBC. Until then you can </span><br/></p>
<p begin = "00:02:53.608" dur="00:00:05.00"><span tts:color="#ededed" tts:textAlign="center"> hour on CBBC. Until then you can <br/> keep </span></p>
<p begin = "00:02:53.808" dur="00:00:05.00"><span tts:color="#ededed" tts:textAlign="center"> hour on CBBC. Until then you can <br/> keep up-to-date </span></p>
<p begin = "00:02:55.406" dur="00:00:05.00"><span tts:color="#ededed" tts:textAlign="center"> hour on CBBC. Until then you can <br/> keep up-to-date with </span></p>
<p begin = "00:02:55.606" dur="00:00:05.00"><span tts:color="#ededed" tts:textAlign="center"> hour on CBBC. Until then you can <br/> keep up-to-date with the </span></p>
<p begin = "00:02:55.846" dur="00:00:05.00"><span tts:color="#ededed" tts:textAlign="center"> hour on CBBC. Until then you can <br/> keep up-to-date with the website. </span></p>
<p begin = "00:03:47.709" dur="00:00:05.00"><span tts:color="#fefe00" tts:textAlign="center"> Is your bedroom bursting with bulge? </span><br/></p>
<p begin = "00:03:47.709" dur="00:00:05.00"><span tts:color="#ededed" tts:textAlign="center"> Is your bedroom bursting with bulge? <br/> Are you a little bit of a hoarder? </span></p>
</div>
</body></tt>